acqdp/__init__.py
acqdp/circuit/__init__.py
acqdp/circuit/circuit.py
acqdp/circuit/converter.py
acqdp/circuit/noise.py
acqdp/tensor_network/__init__.py
acqdp/tensor_network/compiler.py
acqdp/tensor_network/contraction.py
acqdp/tensor_network/contraction_tree.py
acqdp/tensor_network/contractor.py
acqdp/tensor_network/default_params.json
acqdp/tensor_network/kahypar_order_finder.py
acqdp/tensor_network/khp_params.json
acqdp/tensor_network/local_optimizer.py
acqdp/tensor_network/order_finder.py
acqdp/tensor_network/slicer.py
acqdp/tensor_network/tensor.py
acqdp/tensor_network/tensor_network.py
acqdp/tensor_network/tensor_sum.py
acqdp/tensor_network/tensor_valued.py
acqdp/tensor_network/tensor_view.py
acqdp/tensor_network/undirected_contraction_tree.py
acqdp/tensor_network/kahypar_profiles/cut_kKaHyPar_dissertation.ini
acqdp/tensor_network/kahypar_profiles/cut_kKaHyPar_sea20.ini
acqdp/tensor_network/kahypar_profiles/cut_rKaHyPar_dissertation.ini
acqdp/tensor_network/kahypar_profiles/cut_rKaHyPar_sea20.ini
acqdp/tensor_network/kahypar_profiles/km1_kKaHyPar_dissertation.ini
acqdp/tensor_network/kahypar_profiles/km1_kKaHyPar_sea20.ini
acqdp/tensor_network/kahypar_profiles/km1_rKaHyPar_dissertation.ini
acqdp/tensor_network/kahypar_profiles/km1_rKaHyPar_sea20.ini
acqdp/utility/__init__.py
acqdp/utility/opt_einsum_ext.py
acqdp/utility/opt_einsum_helpers.c
acqdp/utility/opt_einsum_helpers.cpython-37m-darwin.so
acqdp/utility/opt_einsum_helpers.pyx
acqdp/utility/opt_einsum_paths.c
acqdp/utility/opt_einsum_paths.cpython-37m-darwin.so
acqdp/utility/opt_einsum_paths.pyx
acqdp-0.1.1.dist-info/LICENSE
acqdp-0.1.1.dist-info/METADATA
acqdp-0.1.1.dist-info/WHEEL
acqdp-0.1.1.dist-info/top_level.txt
acqdp-0.1.1.dist-info/RECORD
