Metadata-Version: 2.1
Name: acqdp
Version: 0.1.1
Summary: Alibaba Cloud Quantum Development Platform
Home-page: https://github.com/alibaba/acqdp
Author: Alibaba Quantum Lab
Author-email: aql_software@alibabacloud.com
License: MIT
Platform: UNKNOWN
Requires-Python: >=3.7
Requires-Dist: numpy
Requires-Dist: scipy
Requires-Dist: networkx
Requires-Dist: numexpr
Requires-Dist: matplotlib
Requires-Dist: opt-einsum
Requires-Dist: kahypar
Requires-Dist: cma
Requires-Dist: jax
Requires-Dist: jaxlib
Requires-Dist: tqdm
